{
  "project_info": {
    "project_number": "88460218112",
    "project_id": "agrisync-6151b",
    "storage_bucket": "agrisync-6151b.firebasestorage.app"
  },
  "client": [
    {
      "client_info": {
        "mobilesdk_app_id": "1:88460218112:android:5512b3d3fe1edfbb732de5",
        "android_client_info": {
          "package_name": "com.kjoel.agrisync"
        }
      },
      "oauth_client": [],
      "api_key": [
        {
          "current_key": "AIzaSyDrjPn43MJZZv9RO6ZU7OBRQb64TcIzKYc"
        }
      ],
      "services": {
        "appinvite_service": {
          "other_platform_oauth_client": []
        }
      }
    }
  ],
  "configuration_version": "1"
}